smileql/__init__.py
smileql/accounts.py
smileql/authentication.py
smileql/client.py
smileql/introspection.py
smileql/payments.py
smileql/transport.py
Inomial_Smile_GraphQL_Interface-1.0.4.dist-info/METADATA
Inomial_Smile_GraphQL_Interface-1.0.4.dist-info/WHEEL
Inomial_Smile_GraphQL_Interface-1.0.4.dist-info/top_level.txt
Inomial_Smile_GraphQL_Interface-1.0.4.dist-info/RECORD
